{
    "nome": "Dokyuu Hentai HxEros OVA",
    "slug": "dokyuu-hentai-hxeros-ova",
    "imagem": "https://animefire.plus/img/animes/dokyuu-hentai-hxeros-ova.webp",
    "total_episodios": 2,
    "episodios": [
        {
            "numero": 1,
            "url": "https://lightspeedst.net/s2/mp4/dokyuu-hentai-hxeros-ova/hd/1.mp4"
        },
        {
            "numero": 2,
            "url": "https://lightspeedst.net/s2/mp4/dokyuu-hentai-hxeros-ova/hd/2.mp4"
        }
    ],
    "metadata_completo": {
        "titulo_oficial": "Dokyuu Hentai HxEros OVA",
        "titulo_ingles": null,
        "generos": [
            "Action",
            "Comedy",
            "Sci-Fi",
            "Ecchi"
        ],
        "classificacao": "R+ - Mild Nudity",
        "popularidade": 5375,
        "nota_media": 6.22,
        "sinopse": "The first original video episode will follow three of the main heroines in an original story.\n\nBundled with the 11th and 12th volumes of the Dokyuu Hentai HxEros manga.\n\n(Source: MAL News)",
        "ano": null,
        "status": "Finished Airing",
        "imagem_capa": "https://cdn.myanimelist.net/images/anime/1592/109081.jpg",
        "id_mal": 42803
    },
    "generos": [
        "Action",
        "Comedy",
        "Sci-Fi",
        "Ecchi"
    ],
    "nota": 6.22,
    "ano": null
}