{
    "nome": "Hetalia: The World Twinkle Extra Disc",
    "slug": "hetalia-the-world-twinkle-extra-disc",
    "imagem": "https://animefire.plus/img/animes/hetalia-the-world-twinkle-extra-disc.webp",
    "total_episodios": 1,
    "episodios": [
        {
            "numero": 1,
            "url": "https://www.blogger.com/video.g?token=AD6v5dxtmSOPyqAkY0IpJP2jVlUptT_yhuUnqkqKohcHQYIJqt0LtROhk6MYYBxLgrEwMA9aaL2pIejKQatTu9RheoByA5Vcsp1uUQNwV5jtB7E9fRtZXph2G_9s9Bztonnqa9jdFt8"
        }
    ],
    "metadata_completo": {
        "titulo_oficial": "Hetalia: The World Twinkle Extra Disc",
        "titulo_ingles": null,
        "generos": [
            "Comedy"
        ],
        "classificacao": "PG-13 - Teens 13 or older",
        "popularidade": 7428,
        "nota_media": 7.26,
        "sinopse": "It's Halloween, and America decides to invite all the other countries to his party. Since there is a costume contest, the countries show up in a wide array of outfits, although it quickly becomes clear that some among them may have taken the competition a bit too seriously. But soon, the guests begin to wonder why America hasn't shown off his own costume. What could be the reason?\n\n[Written by MAL Rewrite]",
        "ano": null,
        "status": "Finished Airing",
        "imagem_capa": "https://cdn.myanimelist.net/images/anime/10/77986.jpg",
        "id_mal": 31997
    },
    "generos": [
        "Comedy"
    ],
    "nota": 7.26,
    "ano": null
}