{
    "nome": "Ijime: Ikenie no Kyoushitsu",
    "slug": "ijime-ikenie-no-kyoushitsu",
    "imagem": "https://animefire.plus/img/animes/ijime-ikenie-no-kyoushitsu.webp",
    "total_episodios": 1,
    "episodios": [
        {
            "numero": 1,
            "url": "https://lightspeedst.net/s4/mp4/ijime-ikenie-no-kyoushitsu/sd/1.mp4"
        }
    ],
    "metadata_completo": {
        "titulo_oficial": "Ijime: Ikenie no Kyoushitsu",
        "titulo_ingles": null,
        "generos": [
            "Drama"
        ],
        "classificacao": "PG-13 - Teens 13 or older",
        "popularidade": 12254,
        "nota_media": 5.01,
        "sinopse": "The March issue of Shogakukan's Ciao shoujo magazine bundled a DVD with a special anime of Igarashi Kaoru's Ijime manga.",
        "ano": null,
        "status": "Finished Airing",
        "imagem_capa": "https://cdn.myanimelist.net/images/anime/8/35317.jpg",
        "id_mal": 12599
    },
    "generos": [
        "Drama"
    ],
    "nota": 5.01,
    "ano": null
}