{
    "nome": "Kakuriyo no Yadomeshi Ni",
    "slug": "kakuriyo-no-yadomeshi-ni",
    "imagem": "https://animefire.plus/img/animes/kakuriyo-no-yadomeshi-ni.webp",
    "total_episodios": 8,
    "episodios": [
        {
            "numero": 1,
            "url": "https://lightspeedst.net/s5/mp4_temp/kakuriyo-no-yadomeshi-ni/1/720p.mp4"
        },
        {
            "numero": 2,
            "url": "https://lightspeedst.net/s5/mp4_temp/kakuriyo-no-yadomeshi-ni/2/720p.mp4"
        },
        {
            "numero": 3,
            "url": "https://lightspeedst.net/s5/mp4_temp/kakuriyo-no-yadomeshi-ni/3/720p.mp4"
        },
        {
            "numero": 4,
            "url": "https://lightspeedst.net/s5/mp4/kakuriyo-no-yadomeshi-ni/hd/4.mp4"
        },
        {
            "numero": 5,
            "url": "https://lightspeedst.net/s5/mp4_temp/kakuriyo-no-yadomeshi-ni/5/720p.mp4"
        },
        {
            "numero": 6,
            "url": "https://lightspeedst.net/s5/mp4_temp/kakuriyo-no-yadomeshi-ni/6/720p.mp4"
        },
        {
            "numero": 7,
            "url": "https://lightspeedst.net/s5/mp4_temp/kakuriyo-no-yadomeshi-ni/7/720p.mp4"
        },
        {
            "numero": 8,
            "url": "https://lightspeedst.net/s5/mp4/kakuriyo-no-yadomeshi-ni/hd/8.mp4"
        }
    ],
    "metadata_completo": {
        "titulo_oficial": "Kakuriyo no Yadomeshi Ni",
        "titulo_ingles": "Kakuriyo -Bed & Breakfast for Spirits- 2",
        "generos": [
            "Drama",
            "Fantasy",
            "Gourmet",
            "Romance"
        ],
        "classificacao": "PG-13 - Teens 13 or older",
        "popularidade": 4928,
        "nota_media": 7.1,
        "sinopse": "Second season of Kakuriyo no Yadomeshi.",
        "ano": 2025,
        "status": "Currently Airing",
        "imagem_capa": "https://cdn.myanimelist.net/images/anime/1619/151364.jpg",
        "id_mal": 58772
    },
    "generos": [
        "Drama",
        "Fantasy",
        "Gourmet",
        "Romance"
    ],
    "nota": 7.1,
    "ano": 2025
}