{
    "nome": "Kibou no Chikara: Otona Precure '23",
    "slug": "kibou-no-chikara-otona-precure-23",
    "imagem": "https://animefire.plus/img/animes/kibou-no-chikara-otona-precure-23.webp",
    "total_episodios": 12,
    "episodios": [
        {
            "numero": 1,
            "url": "https://lightspeedst.net/s6/mp4_temp/kibou-no-chikara-otona-precure-23/1/720p.mp4",
            "nome": "The Shape of the Future"
        },
        {
            "numero": 2,
            "url": "https://lightspeedst.net/s6/mp4/kibou-no-chikara-otona-precure-23/fhd/2.mp4",
            "nome": "The Shape of Determination"
        },
        {
            "numero": 3,
            "url": "https://lightspeedst.net/s6/mp4/kibou-no-chikara-otona-precure-23/fhd/3.mp4",
            "nome": "Memories of the Heart"
        },
        {
            "numero": 4,
            "url": "https://lightspeedst.net/s6/mp4/kibou-no-chikara-otona-precure-23/fhd/4.mp4",
            "nome": "Wings of Doubt"
        },
        {
            "numero": 5,
            "url": "https://lightspeedst.net/s6/mp4/kibou-no-chikara-otona-precure-23/fhd/5.mp4",
            "nome": "Nozomi's Wish"
        },
        {
            "numero": 6,
            "url": "https://lightspeedst.net/s6/mp4/kibou-no-chikara-otona-precure-23/fhd/6.mp4",
            "nome": "The Wavering Flame"
        },
        {
            "numero": 7,
            "url": "https://lightspeedst.net/s6/mp4/kibou-no-chikara-otona-precure-23/fhd/7.mp4",
            "nome": "The Fruit of Sadness"
        },
        {
            "numero": 8,
            "url": "https://lightspeedst.net/s6/mp4/kibou-no-chikara-otona-precure-23/fhd/8.mp4",
            "nome": "My Town"
        },
        {
            "numero": 9,
            "url": "https://lightspeedst.net/s6/mp4/kibou-no-chikara-otona-precure-23/fhd/9.mp4",
            "nome": "Their Bond"
        },
        {
            "numero": 10,
            "url": "https://lightspeedst.net/s6/mp4/kibou-no-chikara-otona-precure-23/fhd/10.mp4",
            "nome": "The Last Promise"
        },
        {
            "numero": 11,
            "url": "https://lightspeedst.net/s6/mp4/kibou-no-chikara-otona-precure-23/fhd/11.mp4",
            "nome": "The End of the Future"
        },
        {
            "numero": 12,
            "url": "https://lightspeedst.net/s6/mp4/kibou-no-chikara-otona-precure-23/fhd/12.mp4",
            "nome": "The Power of Hope"
        }
    ],
    "metadata_completo": {
        "titulo_oficial": "Kibou no Chikara: Otona Precure '23",
        "titulo_ingles": "Power of Hope ~Precure Full Bloom~",
        "generos": [
            "Action"
        ],
        "classificacao": "PG-13 - Teens 13 or older",
        "popularidade": 7186,
        "nota_media": 6.55,
        "sinopse": "When Nozomi Yumehara was a very ordinary middle school student, she met the mysterious fairy Coco, who had come from Palmier Kingdom. In order to protect everyone's hopes, she became the Precure of Hope, Cure Dream, and fought against powerful enemies alongside her friends. Years later, Nozomi and her friends are now adults. They are all busy and enjoying their work, private lives, friends, family and love lives, while also stressing over the obstacles and troubles that adult life brings. Then suddenly, the mysterious Shadows appear, attacking humans. At the chiming of the clocktower bell, grown-up Nozomi and her friends embark on a new saga.\n\n(Source: Toei Animation)",
        "ano": 2023,
        "status": "Finished Airing",
        "imagem_capa": "https://cdn.myanimelist.net/images/anime/1192/138182.jpg",
        "id_mal": 54716
    },
    "generos": [
        "Action"
    ],
    "nota": 6.55,
    "ano": 2023
}