{
    "nome": "Minami-ke Natsuyasumi",
    "slug": "minami-ke-natsuyasumi",
    "imagem": "https://animefire.plus/img/animes/minami-ke-natsuyasumi.webp",
    "total_episodios": 1,
    "episodios": [
        {
            "numero": 1,
            "url": "https://lightspeedst.net/s2/mp4/minami-ke-natsuyasumi/sd/1.mp4"
        }
    ],
    "metadata_completo": {
        "titulo_oficial": "Minami-ke Natsuyasumi",
        "titulo_ingles": null,
        "generos": [
            "Comedy"
        ],
        "classificacao": "PG-13 - Teens 13 or older",
        "popularidade": 5405,
        "nota_media": 7.36,
        "sinopse": "Second Minami-ke OVA bundled with the 11th volume of the manga.\n\nChiaki, Kana, and Haruka decide how to spend their last few days of summer together.  Kana struggles to finish her homework.",
        "ano": null,
        "status": "Finished Airing",
        "imagem_capa": "https://cdn.myanimelist.net/images/anime/1053/151780.jpg",
        "id_mal": 20221
    },
    "generos": [
        "Comedy"
    ],
    "nota": 7.36,
    "ano": null
}