{
    "nome": "Spiral: Suiri no Kizuna",
    "slug": "spiral-suiri-no-kizuna",
    "imagem": "https://animefire.plus/img/animes/spiral-suiri-no-kizuna.webp",
    "total_episodios": 25,
    "episodios": [
        {
            "numero": 1,
            "url": "https://lightspeedst.net/s3/mp4/spiral-suiri-no-kizuna/sd/1.mp4"
        },
        {
            "numero": 2,
            "url": "https://lightspeedst.net/s3/mp4/spiral-suiri-no-kizuna/sd/2.mp4"
        },
        {
            "numero": 3,
            "url": "https://lightspeedst.net/s3/mp4/spiral-suiri-no-kizuna/sd/3.mp4"
        },
        {
            "numero": 4,
            "url": "https://lightspeedst.net/s3/mp4/spiral-suiri-no-kizuna/sd/4.mp4"
        },
        {
            "numero": 5,
            "url": "https://lightspeedst.net/s3/mp4/spiral-suiri-no-kizuna/sd/5.mp4"
        },
        {
            "numero": 6,
            "url": "https://lightspeedst.net/s3/mp4/spiral-suiri-no-kizuna/sd/6.mp4"
        },
        {
            "numero": 7,
            "url": "https://lightspeedst.net/s3/mp4/spiral-suiri-no-kizuna/sd/7.mp4"
        },
        {
            "numero": 8,
            "url": "https://lightspeedst.net/s3/mp4/spiral-suiri-no-kizuna/sd/8.mp4"
        },
        {
            "numero": 9,
            "url": "https://lightspeedst.net/s3/mp4/spiral-suiri-no-kizuna/sd/9.mp4"
        },
        {
            "numero": 10,
            "url": "https://lightspeedst.net/s3/mp4/spiral-suiri-no-kizuna/sd/10.mp4"
        },
        {
            "numero": 11,
            "url": "https://lightspeedst.net/s3/mp4/spiral-suiri-no-kizuna/sd/11.mp4"
        },
        {
            "numero": 12,
            "url": "https://lightspeedst.net/s3/mp4/spiral-suiri-no-kizuna/sd/12.mp4"
        },
        {
            "numero": 13,
            "url": "https://lightspeedst.net/s3/mp4/spiral-suiri-no-kizuna/sd/13.mp4"
        },
        {
            "numero": 14,
            "url": "https://lightspeedst.net/s3/mp4/spiral-suiri-no-kizuna/sd/14.mp4"
        },
        {
            "numero": 15,
            "url": "https://lightspeedst.net/s3/mp4/spiral-suiri-no-kizuna/sd/15.mp4"
        },
        {
            "numero": 16,
            "url": "https://lightspeedst.net/s3/mp4/spiral-suiri-no-kizuna/sd/16.mp4"
        },
        {
            "numero": 17,
            "url": "https://lightspeedst.net/s3/mp4/spiral-suiri-no-kizuna/sd/17.mp4"
        },
        {
            "numero": 18,
            "url": "https://lightspeedst.net/s3/mp4/spiral-suiri-no-kizuna/sd/18.mp4"
        },
        {
            "numero": 19,
            "url": "https://lightspeedst.net/s3/mp4/spiral-suiri-no-kizuna/sd/19.mp4"
        },
        {
            "numero": 20,
            "url": "https://lightspeedst.net/s3/mp4/spiral-suiri-no-kizuna/sd/20.mp4"
        },
        {
            "numero": 21,
            "url": "https://lightspeedst.net/s3/mp4/spiral-suiri-no-kizuna/sd/21.mp4"
        },
        {
            "numero": 22,
            "url": "https://lightspeedst.net/s3/mp4/spiral-suiri-no-kizuna/sd/22.mp4"
        },
        {
            "numero": 23,
            "url": "https://lightspeedst.net/s3/mp4/spiral-suiri-no-kizuna/sd/23.mp4"
        },
        {
            "numero": 24,
            "url": "https://lightspeedst.net/s3/mp4/spiral-suiri-no-kizuna/sd/24.mp4"
        },
        {
            "numero": 25,
            "url": "https://lightspeedst.net/s3/mp4/spiral-suiri-no-kizuna/sd/25.mp4"
        }
    ],
    "metadata_completo": {
        "titulo_oficial": "Spiral: Suiri no Kizuna",
        "titulo_ingles": "Spiral: Bond of Reasoning",
        "generos": [
            "Drama",
            "Mystery"
        ],
        "classificacao": "PG-13 - Teens 13 or older",
        "popularidade": 3303,
        "nota_media": 7.2,
        "sinopse": "Ayumu Narumi has lived all his life in the shadow of his famous detective brother, Kiyotaka. However, Kiyotaka disappeared two years ago, leaving behind his wife Madoka and Ayumu himself, along with a cryptic message about the \"Blade Children.\"\n\nOne day, a girl at Ayumu's school suddenly dies. What seemed like a suicide at first glance turns out to be a murder, and Ayumu is the prime suspect. While investigating the person responsible for framing him, he discovers that the mysterious Blade Children are involved—and they somehow know Kiyotaka personally. Ayumu soon finds out just how dangerous the Blade Children are and learns that, in reality, he and Kiyotaka are intertwined more closely than he had ever believed.\n\n[Written by MAL Rewrite]",
        "ano": 2002,
        "status": "Finished Airing",
        "imagem_capa": "https://cdn.myanimelist.net/images/anime/1771/92118.jpg",
        "id_mal": 341
    },
    "generos": [
        "Drama",
        "Mystery"
    ],
    "nota": 7.2,
    "ano": 2002
}